[{"inputs":[],"stateMutability":"nonpayable","type":"constructor"},{"inputs":[],"name":"AccessDenied","type":"error"},{"inputs":[{"internalType":"address","name":"target","type":"address"}],"name":"AddressEmptyCode","type":"error"},{"inputs":[{"internalType":"address","name":"account","type":"address"}],"name":"AddressInsufficientBalance","type":"error"},{"inputs":[],"name":"AlreadyInitialized","type":"error"},{"inputs":[],"name":"AuctionAlreadyStarted","type":"error"},{"inputs":[],"name":"AuctionIsOngoing","type":"error"},{"inputs":[],"name":"AuctionNotSucceeded","type":"error"},{"inputs":[],"name":"AuctionPeriodPassed","type":"error"},{"inputs":[],"name":"CallerIsNotAuction","type":"error"},{"inputs":[],"name":"DistributionPeriod","type":"error"},{"inputs":[],"name":"DistributionPeriodNotPassed","type":"error"},{"inputs":[],"name":"EnforcedPause","type":"error"},{"inputs":[],"name":"ExpectedPause","type":"error"},{"inputs":[],"name":"FailedInnerCall","type":"error"},{"inputs":[],"name":"FeeTooHigh","type":"error"},{"inputs":[],"name":"InvalidInitialization","type":"error"},{"inputs":[],"name":"MinAmount","type":"error"},{"inputs":[],"name":"NoFeedFound","type":"error"},{"inputs":[],"name":"NoFeesToClaim","type":"error"},{"inputs":[],"name":"NoPriceFound","type":"error"},{"inputs":[],"name":"NotBeneficiary","type":"error"},{"inputs":[],"name":"NotInitializing","type":"error"},{"inputs":[],"name":"PoolSaleLimitTooLow","type":"error"},{"inputs":[],"name":"ReentrancyGuardReentrantCall","type":"error"},{"inputs":[{"internalType":"address","name":"token","type":"address"}],"name":"SafeERC20FailedOperation","type":"error"},{"inputs":[],"name":"StalePrice","type":"error"},{"inputs":[],"name":"TransactionTooOld","type":"error"},{"inputs":[],"name":"ZeroAmount","type":"error"},{"inputs":[],"name":"ZeroDebtSupply","type":"error"},{"inputs":[],"name":"ZeroLeverageSupply","type":"error"},{"anonymous":false,"inputs":[{"indexed":false,"internalType":"uint256","name":"oldPeriod","type":"uint256"},{"indexed":false,"internalType":"uint256","name":"newPeriod","type":"uint256"}],"name":"AuctionPeriodChanged","type":"event"},{"anonymous":false,"inputs":[{"indexed":false,"internalType":"address","name":"auction","type":"address"},{"indexed":false,"internalType":"uint256","name":"period","type":"uint256"},{"indexed":false,"internalType":"uint256","name":"couponAmountToDistribute","type":"uint256"}],"name":"AuctionStarted","type":"event"},{"anonymous":false,"inputs":[{"indexed":false,"internalType":"uint256","name":"period","type":"uint256"},{"indexed":false,"internalType":"uint256","name":"amount","type":"uint256"}],"name":"Distributed","type":"event"},{"anonymous":false,"inputs":[{"indexed":false,"internalType":"uint256","name":"period","type":"uint256"},{"indexed":false,"internalType":"uint256","name":"amount","type":"uint256"},{"indexed":false,"internalType":"address","name":"distributor","type":"address"}],"name":"Distributed","type":"event"},{"anonymous":false,"inputs":[{"indexed":false,"internalType":"uint256","name":"oldPeriod","type":"uint256"},{"indexed":false,"internalType":"uint256","name":"newPeriod","type":"uint256"}],"name":"DistributionPeriodChanged","type":"event"},{"anonymous":false,"inputs":[{"indexed":false,"internalType":"uint256","name":"period","type":"uint256"},{"indexed":false,"internalType":"uint256","name":"shares","type":"uint256"}],"name":"DistributionRollOver","type":"event"},{"anonymous":false,"inputs":[{"indexed":false,"internalType":"uint256","name":"oldFee","type":"uint256"},{"indexed":false,"internalType":"uint256","name":"newFee","type":"uint256"}],"name":"FeeChanged","type":"event"},{"anonymous":false,"inputs":[{"indexed":false,"internalType":"address","name":"beneficiary","type":"address"},{"indexed":false,"internalType":"uint256","name":"amount","type":"uint256"}],"name":"FeeClaimed","type":"event"},{"anonymous":false,"inputs":[{"indexed":false,"internalType":"uint64","name":"version","type":"uint64"}],"name":"Initialized","type":"event"},{"anonymous":false,"inputs":[{"indexed":false,"internalType":"address","name":"account","type":"address"}],"name":"Paused","type":"event"},{"anonymous":false,"inputs":[{"indexed":false,"internalType":"uint256","name":"oldThreshold","type":"uint256"},{"indexed":false,"internalType":"uint256","name":"newThreshold","type":"uint256"}],"name":"PoolSaleLimitChanged","type":"event"},{"anonymous":false,"inputs":[{"indexed":false,"internalType":"uint256","name":"oldSharesPerToken","type":"uint256"},{"indexed":false,"internalType":"uint256","name":"sharesPerToken","type":"uint256"}],"name":"SharesPerTokenChanged","type":"event"},{"anonymous":false,"inputs":[{"indexed":false,"internalType":"address","name":"caller","type":"address"},{"indexed":true,"internalType":"address","name":"onBehalfOf","type":"address"},{"indexed":false,"internalType":"enum Pool.TokenType","name":"tokenType","type":"uint8"},{"indexed":false,"internalType":"uint256","name":"depositedAmount","type":"uint256"},{"indexed":false,"internalType":"uint256","name":"mintedAmount","type":"uint256"}],"name":"TokensCreated","type":"event"},{"anonymous":false,"inputs":[{"indexed":false,"internalType":"address","name":"caller","type":"address"},{"indexed":true,"internalType":"address","name":"onBehalfOf","type":"address"},{"indexed":false,"internalType":"enum Pool.TokenType","name":"tokenType","type":"uint8"},{"indexed":false,"internalType":"uint256","name":"depositedAmount","type":"uint256"},{"indexed":false,"internalType":"uint256","name":"redeemedAmount","type":"uint256"}],"name":"TokensRedeemed","type":"event"},{"anonymous":false,"inputs":[{"indexed":false,"internalType":"address","name":"account","type":"address"}],"name":"Unpaused","type":"event"},{"inputs":[],"name":"ETH","outputs":[{"internalType":"address","name":"","type":"address"}],"stateMutability":"view","type":"function"},{"inputs":[],"name":"USD","outputs":[{"internalType":"address","name":"","type":"address"}],"stateMutability":"view","type":"function"},{"inputs":[{"internalType":"uint256","name":"","type":"uint256"}],"name":"auctions","outputs":[{"internalType":"address","name":"","type":"address"}],"stateMutability":"view","type":"function"},{"inputs":[],"name":"bondToken","outputs":[{"internalType":"contract BondToken","name":"","type":"address"}],"stateMutability":"view","type":"function"},{"inputs":[],"name":"claimFees","outputs":[],"stateMutability":"nonpayable","type":"function"},{"inputs":[],"name":"couponToken","outputs":[{"internalType":"address","name":"","type":"address"}],"stateMutability":"view","type":"function"},{"inputs":[{"internalType":"enum Pool.TokenType","name":"tokenType","type":"uint8"},{"internalType":"uint256","name":"depositAmount","type":"uint256"},{"internalType":"uint256","name":"minAmount","type":"uint256"}],"name":"create","outputs":[{"internalType":"uint256","name":"","type":"uint256"}],"stateMutability":"nonpayable","type":"function"},{"inputs":[{"internalType":"enum Pool.TokenType","name":"tokenType","type":"uint8"},{"internalType":"uint256","name":"depositAmount","type":"uint256"},{"internalType":"uint256","name":"minAmount","type":"uint256"},{"internalType":"uint256","name":"deadline","type":"uint256"},{"internalType":"address","name":"onBehalfOf","type":"address"}],"name":"create","outputs":[{"internalType":"uint256","name":"","type":"uint256"}],"stateMutability":"nonpayable","type":"function"},{"inputs":[],"name":"distribute","outputs":[],"stateMutability":"nonpayable","type":"function"},{"inputs":[],"name":"feeBeneficiary","outputs":[{"internalType":"address","name":"","type":"address"}],"stateMutability":"view","type":"function"},{"inputs":[{"internalType":"enum Pool.TokenType","name":"tokenType","type":"uint8"},{"internalType":"uint256","name":"depositAmount","type":"uint256"},{"internalType":"uint256","name":"bondSupply","type":"uint256"},{"internalType":"uint256","name":"levSupply","type":"uint256"},{"internalType":"uint256","name":"poolReserves","type":"uint256"},{"internalType":"uint256","name":"ethPrice","type":"uint256"},{"internalType":"uint8","name":"oracleDecimals","type":"uint8"}],"name":"getCreateAmount","outputs":[{"internalType":"uint256","name":"","type":"uint256"}],"stateMutability":"pure","type":"function"},{"inputs":[{"internalType":"address","name":"quote","type":"address"},{"internalType":"address","name":"base","type":"address"}],"name":"getOracleDecimals","outputs":[{"internalType":"uint8","name":"decimals","type":"uint8"}],"stateMutability":"view","type":"function"},{"inputs":[{"internalType":"address","name":"quote","type":"address"},{"internalType":"address","name":"base","type":"address"}],"name":"getOraclePrice","outputs":[{"internalType":"uint256","name":"","type":"uint256"}],"stateMutability":"view","type":"function"},{"inputs":[],"name":"getPoolInfo","outputs":[{"components":[{"internalType":"uint256","name":"fee","type":"uint256"},{"internalType":"uint256","name":"reserve","type":"uint256"},{"internalType":"uint256","name":"bondSupply","type":"uint256"},{"internalType":"uint256","name":"levSupply","type":"uint256"},{"internalType":"uint256","name":"sharesPerToken","type":"uint256"},{"internalType":"uint256","name":"currentPeriod","type":"uint256"},{"internalType":"uint256","name":"lastDistribution","type":"uint256"},{"internalType":"uint256","name":"distributionPeriod","type":"uint256"},{"internalType":"uint256","name":"auctionPeriod","type":"uint256"},{"internalType":"address","name":"feeBeneficiary","type":"address"}],"internalType":"struct Pool.PoolInfo","name":"info","type":"tuple"}],"stateMutability":"view","type":"function"},{"inputs":[{"internalType":"enum Pool.TokenType","name":"tokenType","type":"uint8"},{"internalType":"uint256","name":"depositAmount","type":"uint256"},{"internalType":"uint256","name":"bondSupply","type":"uint256"},{"internalType":"uint256","name":"levSupply","type":"uint256"},{"internalType":"uint256","name":"poolReserves","type":"uint256"},{"internalType":"uint256","name":"ethPrice","type":"uint256"},{"internalType":"uint8","name":"oracleDecimals","type":"uint8"},{"internalType":"uint256","name":"marketRate","type":"uint256"}],"name":"getRedeemAmount","outputs":[{"internalType":"uint256","name":"","type":"uint256"}],"stateMutability":"pure","type":"function"},{"inputs":[{"internalType":"address","name":"_poolFactory","type":"address"},{"internalType":"uint256","name":"_fee","type":"uint256"},{"internalType":"address","name":"_reserveToken","type":"address"},{"internalType":"address","name":"_dToken","type":"address"},{"internalType":"address","name":"_lToken","type":"address"},{"internalType":"address","name":"_couponToken","type":"address"},{"internalType":"uint256","name":"_sharesPerToken","type":"uint256"},{"internalType":"uint256","name":"_distributionPeriod","type":"uint256"},{"internalType":"address","name":"_feeBeneficiary","type":"address"},{"internalType":"address","name":"_oracleFeeds","type":"address"},{"internalType":"bool","name":"_pauseOnCreation","type":"bool"}],"name":"initialize","outputs":[],"stateMutability":"nonpayable","type":"function"},{"inputs":[],"name":"lToken","outputs":[{"internalType":"contract LeverageToken","name":"","type":"address"}],"stateMutability":"view","type":"function"},{"inputs":[],"name":"oracleFeeds","outputs":[{"internalType":"address","name":"","type":"address"}],"stateMutability":"view","type":"function"},{"inputs":[],"name":"pause","outputs":[],"stateMutability":"nonpayable","type":"function"},{"inputs":[],"name":"paused","outputs":[{"internalType":"bool","name":"","type":"bool"}],"stateMutability":"view","type":"function"},{"inputs":[],"name":"poolFactory","outputs":[{"internalType":"contract PoolFactory","name":"","type":"address"}],"stateMutability":"view","type":"function"},{"inputs":[{"internalType":"enum Pool.TokenType","name":"tokenType","type":"uint8"},{"internalType":"uint256","name":"depositAmount","type":"uint256"},{"internalType":"uint256","name":"minAmount","type":"uint256"},{"internalType":"uint256","name":"deadline","type":"uint256"},{"internalType":"address","name":"onBehalfOf","type":"address"}],"name":"redeem","outputs":[{"internalType":"uint256","name":"","type":"uint256"}],"stateMutability":"nonpayable","type":"function"},{"inputs":[{"internalType":"enum Pool.TokenType","name":"tokenType","type":"uint8"},{"internalType":"uint256","name":"depositAmount","type":"uint256"},{"internalType":"uint256","name":"minAmount","type":"uint256"}],"name":"redeem","outputs":[{"internalType":"uint256","name":"","type":"uint256"}],"stateMutability":"nonpayable","type":"function"},{"inputs":[],"name":"reserveToken","outputs":[{"internalType":"address","name":"","type":"address"}],"stateMutability":"view","type":"function"},{"inputs":[{"internalType":"uint256","name":"_auctionPeriod","type":"uint256"}],"name":"setAuctionPeriod","outputs":[],"stateMutability":"nonpayable","type":"function"},{"inputs":[{"internalType":"uint256","name":"_distributionPeriod","type":"uint256"}],"name":"setDistributionPeriod","outputs":[],"stateMutability":"nonpayable","type":"function"},{"inputs":[{"internalType":"uint256","name":"_fee","type":"uint256"}],"name":"setFee","outputs":[],"stateMutability":"nonpayable","type":"function"},{"inputs":[{"internalType":"address","name":"_feeBeneficiary","type":"address"}],"name":"setFeeBeneficiary","outputs":[],"stateMutability":"nonpayable","type":"function"},{"inputs":[{"internalType":"uint256","name":"_poolSaleLimit","type":"uint256"}],"name":"setPoolSaleLimit","outputs":[],"stateMutability":"nonpayable","type":"function"},{"inputs":[{"internalType":"uint256","name":"_sharesPerToken","type":"uint256"}],"name":"setSharesPerToken","outputs":[],"stateMutability":"nonpayable","type":"function"},{"inputs":[{"internalType":"enum Pool.TokenType","name":"tokenType","type":"uint8"},{"internalType":"uint256","name":"depositAmount","type":"uint256"}],"name":"simulateCreate","outputs":[{"internalType":"uint256","name":"","type":"uint256"}],"stateMutability":"view","type":"function"},{"inputs":[{"internalType":"enum Pool.TokenType","name":"tokenType","type":"uint8"},{"internalType":"uint256","name":"depositAmount","type":"uint256"}],"name":"simulateRedeem","outputs":[{"internalType":"uint256","name":"","type":"uint256"}],"stateMutability":"view","type":"function"},{"inputs":[],"name":"startAuction","outputs":[],"stateMutability":"nonpayable","type":"function"},{"inputs":[{"internalType":"uint256","name":"amount","type":"uint256"}],"name":"transferReserveToAuction","outputs":[],"stateMutability":"nonpayable","type":"function"},{"inputs":[],"name":"unpause","outputs":[],"stateMutability":"nonpayable","type":"function"}]